balpy_v2/__init__.py
balpy_v2/contracts/__init__.py
balpy_v2/contracts/utils/base_contract.py
balpy_v2/contracts/utils/contract_loader.py
balpy_v2/deployments/.keep
balpy_v2/lib/__init__.py
balpy_v2/lib/gql.py
balpy_v2/lib/llama/__init__.py
balpy_v2/lib/time.py
balpy_v2/lib/web3_provider.py
balpy_v2/subgraphs/__init__.py
balpy_v2/subgraphs/balancer.py
balpy_v2/subgraphs/blocks.py
balpy_v2/subgraphs/client.py
balpy_v2/subgraphs/gauges.py
balpy_v2/subgraphs/query.py
balpy_v2-0.1.2.dist-info/METADATA
balpy_v2-0.1.2.dist-info/WHEEL
balpy_v2-0.1.2.dist-info/RECORD
