Metadata-Version: 2.1
Name: balpy-v2
Version: 0.1.2
Summary: 
Author: José Ribeiro
Author-email: me@joseribeiro.dev
Requires-Python: >=3.11,<4.0
Classifier: Programming Language :: Python :: 3
Classifier: Programming Language :: Python :: 3.11
Requires-Dist: async-lru (>=2.0.2,<3.0.0)
Requires-Dist: httpx (>=0.24.0,<0.25.0)
Requires-Dist: numpy (>=1.24.3,<2.0.0)
Requires-Dist: pandas (>=2.0.1,<3.0.0)
Requires-Dist: web3 (>=6.3.0,<7.0.0)
